{"resources":{"Scripts/Connection_test(root).sql":{"sql-editor-data-source-id":"mysql5-17032b702b1-1694ddebd4c87eb9","default-catalog":"jdbc_pool_study"},"Scripts/Connection_test(user).sql":{"sql-editor-data-source-id":"mysql5-17032b7a8b1-6565a4404823f80f","default-catalog":"jdbc_pool_study"},"Scripts/data.sql":{"sql-editor-data-source-id":"mysql5-17032b7a8b1-6565a4404823f80f","default-catalog":"jdbc_pool_study"},"Scripts/data_access_object.sql":{"sql-editor-data-source-id":"mysql5-17032b7a8b1-6565a4404823f80f","default-catalog":"jdbc_pool_study"},"Scripts/init.sql":{"sql-editor-data-source-id":"mysql5-17032b702b1-1694ddebd4c87eb9","default-catalog":"jdbc_pool_study"}}}